{
    "id": 10230, 
    "sources": [
        {
            "count": 2, 
            "name": "aria2c"
        }, 
        {
            "count": 2, 
            "name": "simutrans"
        }, 
        {
            "count": 28, 
            "name": "mednafen"
        }, 
        {
            "count": 2, 
            "name": "nomacs"
        }, 
        {
            "count": 4, 
            "name": "exonpairs"
        }, 
        {
            "count": 4, 
            "name": "fathom"
        }, 
        {
            "count": 4, 
            "name": "forge"
        }, 
        {
            "count": 4, 
            "name": "hmm-info"
        }, 
        {
            "count": 4, 
            "name": "zoe-loop"
        }, 
        {
            "count": 4, 
            "name": "snap"
        }
    ]
}