{
    "id": 32071, 
    "sources": [
        {
            "count": 12, 
            "name": "libc-2.23.so"
        }, 
        {
            "count": 20, 
            "name": "gnome-panel"
        }, 
        {
            "count": 956, 
            "name": "libgobject-2.0.so.0.4800.2"
        }, 
        {
            "count": 2, 
            "name": "battstat-applet-2"
        }, 
        {
            "count": 2, 
            "name": "geyes_applet2"
        }, 
        {
            "count": 4, 
            "name": "tracker-search-bar"
        }, 
        {
            "count": 140, 
            "name": "libxml2.so.2.9.3"
        }, 
        {
            "count": 2, 
            "name": "cupstestdsc"
        }, 
        {
            "count": 20, 
            "name": "cupstestppd"
        }, 
        {
            "count": 4, 
            "name": "lpoptions"
        }, 
        {
            "count": 94, 
            "name": "libcups.so.2"
        }, 
        {
            "count": 6, 
            "name": "libz.so.1.2.8"
        }, 
        {
            "count": 228, 
            "name": "transmission-gtk"
        }, 
        {
            "count": 10, 
            "name": "umax_pp"
        }, 
        {
            "count": 24, 
            "name": "lpd"
        }, 
        {
            "count": 24, 
            "name": "socket"
        }, 
        {
            "count": 4, 
            "name": "admin.cgi"
        }, 
        {
            "count": 2, 
            "name": "cups-lpd"
        }, 
        {
            "count": 6, 
            "name": "bcp"
        }, 
        {
            "count": 4, 
            "name": "tbcp"
        }, 
        {
            "count": 2, 
            "name": "l2ping"
        }, 
        {
            "count": 2, 
            "name": "bluetoothd"
        }, 
        {
            "count": 2, 
            "name": "glxheads"
        }, 
        {
            "count": 2, 
            "name": "libpulsecommon-8.0.so"
        }, 
        {
            "count": 40, 
            "name": "libdevmapper.so.1.02.1"
        }, 
        {
            "count": 10, 
            "name": "grub-editenv"
        }, 
        {
            "count": 70, 
            "name": "grub-file"
        }, 
        {
            "count": 70, 
            "name": "grub-fstest"
        }, 
        {
            "count": 10, 
            "name": "grub-glue-efi"
        }, 
        {
            "count": 12, 
            "name": "grub-menulst2cfg"
        }, 
        {
            "count": 10, 
            "name": "grub-mkfont"
        }, 
        {
            "count": 20, 
            "name": "grub-mkimage"
        }, 
        {
            "count": 10, 
            "name": "grub-mklayout"
        }, 
        {
            "count": 26, 
            "name": "grub-mknetdir"
        }, 
        {
            "count": 10, 
            "name": "grub-mkpasswd-pbkdf2"
        }, 
        {
            "count": 10, 
            "name": "grub-mkrelpath"
        }, 
        {
            "count": 86, 
            "name": "grub-mkrescue"
        }, 
        {
            "count": 26, 
            "name": "grub-mkstandalone"
        }, 
        {
            "count": 70, 
            "name": "grub-mount"
        }, 
        {
            "count": 70, 
            "name": "grub-render-label"
        }, 
        {
            "count": 12, 
            "name": "grub-script-check"
        }, 
        {
            "count": 72, 
            "name": "grub-syslinux2cfg"
        }, 
        {
            "count": 70, 
            "name": "grub-macbless"
        }, 
        {
            "count": 10, 
            "name": "grub-mkdevicemap"
        }, 
        {
            "count": 72, 
            "name": "grub-probe"
        }, 
        {
            "count": 10, 
            "name": "mtools"
        }, 
        {
            "count": 6, 
            "name": "syslinux"
        }, 
        {
            "count": 6, 
            "name": "dnsmasq"
        }, 
        {
            "count": 20, 
            "name": "rarian-sk-get-cl"
        }, 
        {
            "count": 20, 
            "name": "rarian-sk-migrate"
        }, 
        {
            "count": 10, 
            "name": "rarian-sk-preinstall"
        }, 
        {
            "count": 2, 
            "name": "librarian.so.0.0.0"
        }, 
        {
            "count": 16, 
            "name": "https"
        }, 
        {
            "count": 20, 
            "name": "libapt-pkg.so.5.0.0"
        }, 
        {
            "count": 16, 
            "name": "lzmp"
        }
    ]
}