{
    "id": 32855, 
    "sources": [
        {
            "count": 1316, 
            "name": "sed"
        }, 
        {
            "count": 775702, 
            "name": "libc-2.23.so"
        }, 
        {
            "count": 8160, 
            "name": "libselinux.so.1"
        }, 
        {
            "count": 10, 
            "name": "libdebconfclient.so.0.0.0"
        }, 
        {
            "count": 346, 
            "name": "update-passwd"
        }, 
        {
            "count": 3058, 
            "name": "libtinfo.so.5.9"
        }, 
        {
            "count": 14, 
            "name": "clear"
        }, 
        {
            "count": 390, 
            "name": "infocmp"
        }, 
        {
            "count": 60, 
            "name": "tabs"
        }, 
        {
            "count": 540, 
            "name": "tic"
        }, 
        {
            "count": 90, 
            "name": "toe"
        }, 
        {
            "count": 82, 
            "name": "tput"
        }, 
        {
            "count": 112, 
            "name": "tset"
        }, 
        {
            "count": 346, 
            "name": "libtic.so.5.9"
        }, 
        {
            "count": 120, 
            "name": "hostname"
        }, 
        {
            "count": 4, 
            "name": "libnsl-2.23.so"
        }, 
        {
            "count": 888, 
            "name": "cat"
        }, 
        {
            "count": 1008, 
            "name": "chgrp"
        }, 
        {
            "count": 988, 
            "name": "chmod"
        }, 
        {
            "count": 1062, 
            "name": "chown"
        }, 
        {
            "count": 2760, 
            "name": "cp"
        }, 
        {
            "count": 1058, 
            "name": "date"
        }, 
        {
            "count": 1142, 
            "name": "dd"
        }, 
        {
            "count": 1738, 
            "name": "df"
        }, 
        {
            "count": 1806, 
            "name": "dir"
        }, 
        {
            "count": 390, 
            "name": "echo"
        }, 
        {
            "count": 368, 
            "name": "false"
        }, 
        {
            "count": 1078, 
            "name": "ln"
        }, 
        {
            "count": 1856, 
            "name": "ls"
        }, 
        {
            "count": 1402, 
            "name": "mkdir"
        }, 
        {
            "count": 1184, 
            "name": "mknod"
        }, 
        {
            "count": 648, 
            "name": "mktemp"
        }, 
        {
            "count": 2510, 
            "name": "mv"
        }, 
        {
            "count": 504, 
            "name": "pwd"
        }, 
        {
            "count": 714, 
            "name": "readlink"
        }, 
        {
            "count": 1104, 
            "name": "rm"
        }, 
        {
            "count": 606, 
            "name": "rmdir"
        }, 
        {
            "count": 422, 
            "name": "sleep"
        }, 
        {
            "count": 1026, 
            "name": "stty"
        }, 
        {
            "count": 384, 
            "name": "sync"
        }, 
        {
            "count": 784, 
            "name": "touch"
        }, 
        {
            "count": 368, 
            "name": "true"
        }, 
        {
            "count": 424, 
            "name": "uname"
        }, 
        {
            "count": 1806, 
            "name": "vdir"
        }, 
        {
            "count": 754, 
            "name": "libacl.so.1.1.0"
        }, 
        {
            "count": 758, 
            "name": "libattr.so.1.1.0"
        }, 
        {
            "count": 600, 
            "name": "libpthread-2.23.so"
        }, 
        {
            "count": 68, 
            "name": "librt-2.23.so"
        }, 
        {
            "count": 752, 
            "name": "["
        }, 
        {
            "count": 410, 
            "name": "arch"
        }, 
        {
            "count": 484, 
            "name": "base32"
        }, 
        {
            "count": 482, 
            "name": "base64"
        }, 
        {
            "count": 434, 
            "name": "basename"
        }, 
        {
            "count": 1078, 
            "name": "chcon"
        }, 
        {
            "count": 420, 
            "name": "cksum"
        }, 
        {
            "count": 530, 
            "name": "comm"
        }, 
        {
            "count": 722, 
            "name": "csplit"
        }, 
        {
            "count": 534, 
            "name": "cut"
        }, 
        {
            "count": 526, 
            "name": "dircolors"
        }, 
        {
            "count": 416, 
            "name": "dirname"
        }, 
        {
            "count": 2130, 
            "name": "du"
        }, 
        {
            "count": 388, 
            "name": "env"
        }, 
        {
            "count": 436, 
            "name": "expand"
        }, 
        {
            "count": 666, 
            "name": "expr"
        }, 
        {
            "count": 1190, 
            "name": "factor"
        }, 
        {
            "count": 486, 
            "name": "fmt"
        }, 
        {
            "count": 436, 
            "name": "fold"
        }, 
        {
            "count": 426, 
            "name": "groups"
        }, 
        {
            "count": 664, 
            "name": "head"
        }, 
        {
            "count": 376, 
            "name": "hostid"
        }, 
        {
            "count": 588, 
            "name": "id"
        }, 
        {
            "count": 2608, 
            "name": "install"
        }, 
        {
            "count": 720, 
            "name": "join"
        }, 
        {
            "count": 394, 
            "name": "link"
        }, 
        {
            "count": 386, 
            "name": "logname"
        }, 
        {
            "count": 576, 
            "name": "md5sum"
        }, 
        {
            "count": 1114, 
            "name": "mkfifo"
        }, 
        {
            "count": 428, 
            "name": "nice"
        }, 
        {
            "count": 502, 
            "name": "nl"
        }, 
        {
            "count": 442, 
            "name": "nohup"
        }, 
        {
            "count": 412, 
            "name": "nproc"
        }, 
        {
            "count": 818, 
            "name": "numfmt"
        }, 
        {
            "count": 882, 
            "name": "od"
        }, 
        {
            "count": 418, 
            "name": "paste"
        }, 
        {
            "count": 428, 
            "name": "pathchk"
        }, 
        {
            "count": 538, 
            "name": "pinky"
        }, 
        {
            "count": 1006, 
            "name": "pr"
        }, 
        {
            "count": 372, 
            "name": "printenv"
        }, 
        {
            "count": 734, 
            "name": "printf"
        }, 
        {
            "count": 1032, 
            "name": "ptx"
        }, 
        {
            "count": 1108, 
            "name": "realpath"
        }, 
        {
            "count": 464, 
            "name": "runcon"
        }, 
        {
            "count": 674, 
            "name": "seq"
        }, 
        {
            "count": 576, 
            "name": "sha1sum"
        }, 
        {
            "count": 618, 
            "name": "sha224sum"
        }, 
        {
            "count": 618, 
            "name": "sha256sum"
        }, 
        {
            "count": 1378, 
            "name": "sha384sum"
        }, 
        {
            "count": 1378, 
            "name": "sha512sum"
        }, 
        {
            "count": 828, 
            "name": "shred"
        }, 
        {
            "count": 880, 
            "name": "shuf"
        }, 
        {
            "count": 1872, 
            "name": "sort"
        }, 
        {
            "count": 1166, 
            "name": "split"
        }, 
        {
            "count": 1264, 
            "name": "stat"
        }, 
        {
            "count": 1040, 
            "name": "stdbuf"
        }, 
        {
            "count": 524, 
            "name": "sum"
        }, 
        {
            "count": 542, 
            "name": "tac"
        }, 
        {
            "count": 1206, 
            "name": "tail"
        }, 
        {
            "count": 462, 
            "name": "tee"
        }, 
        {
            "count": 698, 
            "name": "test"
        }, 
        {
            "count": 846, 
            "name": "timeout"
        }, 
        {
            "count": 636, 
            "name": "tr"
        }, 
        {
            "count": 856, 
            "name": "truncate"
        }, 
        {
            "count": 480, 
            "name": "tsort"
        }, 
        {
            "count": 376, 
            "name": "tty"
        }, 
        {
            "count": 442, 
            "name": "unexpand"
        }, 
        {
            "count": 602, 
            "name": "uniq"
        }, 
        {
            "count": 392, 
            "name": "unlink"
        }, 
        {
            "count": 410, 
            "name": "users"
        }, 
        {
            "count": 650, 
            "name": "wc"
        }, 
        {
            "count": 674, 
            "name": "who"
        }, 
        {
            "count": 384, 
            "name": "whoami"
        }, 
        {
            "count": 404, 
            "name": "yes"
        }, 
        {
            "count": 528, 
            "name": "chroot"
        }, 
        {
            "count": 3770, 
            "name": "find"
        }, 
        {
            "count": 976, 
            "name": "xargs"
        }, 
        {
            "count": 272, 
            "name": "libsystemd.so.0.14.0"
        }, 
        {
            "count": 54, 
            "name": "libutil-2.23.so"
        }, 
        {
            "count": 582, 
            "name": "logger"
        }, 
        {
            "count": 106, 
            "name": "renice"
        }, 
        {
            "count": 208, 
            "name": "script"
        }, 
        {
            "count": 116, 
            "name": "scriptreplay"
        }, 
        {
            "count": 446, 
            "name": "wall"
        }, 
        {
            "count": 7842, 
            "name": "tar"
        }, 
        {
            "count": 944, 
            "name": "rmt-tar"
        }, 
        {
            "count": 4112, 
            "name": "grep"
        }, 
        {
            "count": 352, 
            "name": "libdl-2.23.so"
        }, 
        {
            "count": 100, 
            "name": "libpcre.so.3.13.2"
        }, 
        {
            "count": 834, 
            "name": "gzip"
        }, 
        {
            "count": 3562, 
            "name": "libblkid.so.1.1.0"
        }, 
        {
            "count": 350, 
            "name": "libcom_err.so.2.1"
        }, 
        {
            "count": 436, 
            "name": "libe2p.so.2.3"
        }, 
        {
            "count": 17418, 
            "name": "libext2fs.so.2.4"
        }, 
        {
            "count": 238, 
            "name": "libss.so.2.0"
        }, 
        {
            "count": 140, 
            "name": "libuuid.so.1.3.0"
        }, 
        {
            "count": 308, 
            "name": "badblocks"
        }, 
        {
            "count": 1946, 
            "name": "debugfs"
        }, 
        {
            "count": 238, 
            "name": "dumpe2fs"
        }, 
        {
            "count": 5816, 
            "name": "e2fsck"
        }, 
        {
            "count": 358, 
            "name": "e2image"
        }, 
        {
            "count": 124, 
            "name": "e2undo"
        }, 
        {
            "count": 50, 
            "name": "logsave"
        }, 
        {
            "count": 1940, 
            "name": "mke2fs"
        }, 
        {
            "count": 658, 
            "name": "resize2fs"
        }, 
        {
            "count": 1168, 
            "name": "tune2fs"
        }, 
        {
            "count": 70, 
            "name": "chattr"
        }, 
        {
            "count": 62, 
            "name": "lsattr"
        }, 
        {
            "count": 78, 
            "name": "e2freefrag"
        }, 
        {
            "count": 286, 
            "name": "e4defrag"
        }, 
        {
            "count": 88, 
            "name": "filefrag"
        }, 
        {
            "count": 22, 
            "name": "mklost+found"
        }, 
        {
            "count": 106586, 
            "name": "perl"
        }, 
        {
            "count": 106586, 
            "name": "perl5.22.1"
        }, 
        {
            "count": 23886, 
            "name": "bash"
        }, 
        {
            "count": 34, 
            "name": "clear_console"
        }, 
        {
            "count": 810, 
            "name": "dmesg"
        }, 
        {
            "count": 1442, 
            "name": "lsblk"
        }, 
        {
            "count": 392, 
            "name": "more"
        }, 
        {
            "count": 124, 
            "name": "mountpoint"
        }, 
        {
            "count": 376, 
            "name": "tailf"
        }, 
        {
            "count": 458, 
            "name": "wdctl"
        }, 
        {
            "count": 5570, 
            "name": "libfdisk.so.1.1.0"
        }, 
        {
            "count": 9372, 
            "name": "libmount.so.1.1.0"
        }, 
        {
            "count": 1176, 
            "name": "libncursesw.so.5.9"
        }, 
        {
            "count": 60, 
            "name": "libpam_misc.so.0.82.0"
        }, 
        {
            "count": 862, 
            "name": "libpam.so.0.83.1"
        }, 
        {
            "count": 6168, 
            "name": "libsmartcols.so.1.1.0"
        }, 
        {
            "count": 438, 
            "name": "libudev.so.1.6.4"
        }, 
        {
            "count": 3918, 
            "name": "libz.so.1.2.8"
        }, 
        {
            "count": 518, 
            "name": "agetty"
        }, 
        {
            "count": 392, 
            "name": "blkdiscard"
        }, 
        {
            "count": 1632, 
            "name": "blkid"
        }, 
        {
            "count": 566, 
            "name": "blockdev"
        }, 
        {
            "count": 1156, 
            "name": "cfdisk"
        }, 
        {
            "count": 284, 
            "name": "chcpu"
        }, 
        {
            "count": 74, 
            "name": "ctrlaltdel"
        }, 
        {
            "count": 2198, 
            "name": "fdisk"
        }, 
        {
            "count": 76, 
            "name": "findfs"
        }, 
        {
            "count": 800, 
            "name": "fsck"
        }, 
        {
            "count": 562, 
            "name": "fsck.cramfs"
        }, 
        {
            "count": 1596, 
            "name": "fsck.minix"
        }, 
        {
            "count": 106, 
            "name": "fsfreeze"
        }, 
        {
            "count": 866, 
            "name": "fstrim"
        }, 
        {
            "count": 942, 
            "name": "hwclock"
        }, 
        {
            "count": 350, 
            "name": "isosize"
        }, 
        {
            "count": 102, 
            "name": "mkfs"
        }, 
        {
            "count": 422, 
            "name": "mkfs.bfs"
        }, 
        {
            "count": 552, 
            "name": "mkfs.cramfs"
        }, 
        {
            "count": 1620, 
            "name": "mkfs.minix"
        }, 
        {
            "count": 1580, 
            "name": "mkswap"
        }, 
        {
            "count": 78, 
            "name": "pivot_root"
        }, 
        {
            "count": 136, 
            "name": "raw"
        }, 
        {
            "count": 290, 
            "name": "runuser"
        }, 
        {
            "count": 1938, 
            "name": "sfdisk"
        }, 
        {
            "count": 672, 
            "name": "sulogin"
        }, 
        {
            "count": 142, 
            "name": "swaplabel"
        }, 
        {
            "count": 126, 
            "name": "switch_root"
        }, 
        {
            "count": 492, 
            "name": "wipefs"
        }, 
        {
            "count": 1760, 
            "name": "zramctl"
        }, 
        {
            "count": 330, 
            "name": "addpart"
        }, 
        {
            "count": 484, 
            "name": "chrt"
        }, 
        {
            "count": 324, 
            "name": "delpart"
        }, 
        {
            "count": 400, 
            "name": "fallocate"
        }, 
        {
            "count": 426, 
            "name": "flock"
        }, 
        {
            "count": 168, 
            "name": "getopt"
        }, 
        {
            "count": 390, 
            "name": "ionice"
        }, 
        {
            "count": 380, 
            "name": "ipcmk"
        }, 
        {
            "count": 424, 
            "name": "ipcrm"
        }, 
        {
            "count": 1048, 
            "name": "ipcs"
        }, 
        {
            "count": 608, 
            "name": "last"
        }, 
        {
            "count": 70, 
            "name": "line"
        }, 
        {
            "count": 1046, 
            "name": "lscpu"
        }, 
        {
            "count": 1074, 
            "name": "lsipc"
        }, 
        {
            "count": 482, 
            "name": "lslocks"
        }, 
        {
            "count": 818, 
            "name": "lslogins"
        }, 
        {
            "count": 416, 
            "name": "mcookie"
        }, 
        {
            "count": 102, 
            "name": "mesg"
        }, 
        {
            "count": 438, 
            "name": "namei"
        }, 
        {
            "count": 438, 
            "name": "nsenter"
        }, 
        {
            "count": 1560, 
            "name": "partx"
        }, 
        {
            "count": 658, 
            "name": "pg"
        }, 
        {
            "count": 450, 
            "name": "prlimit"
        }, 
        {
            "count": 162, 
            "name": "rename.ul"
        }, 
        {
            "count": 784, 
            "name": "resizepart"
        }, 
        {
            "count": 72, 
            "name": "rev"
        }, 
        {
            "count": 162, 
            "name": "setarch"
        }, 
        {
            "count": 88, 
            "name": "setsid"
        }, 
        {
            "count": 706, 
            "name": "setterm"
        }, 
        {
            "count": 494, 
            "name": "taskset"
        }, 
        {
            "count": 180, 
            "name": "unshare"
        }, 
        {
            "count": 190, 
            "name": "utmpdump"
        }, 
        {
            "count": 268, 
            "name": "whereis"
        }, 
        {
            "count": 378, 
            "name": "fdformat"
        }, 
        {
            "count": 430, 
            "name": "ldattach"
        }, 
        {
            "count": 194, 
            "name": "readprofile"
        }, 
        {
            "count": 680, 
            "name": "rtcwake"
        }, 
        {
            "count": 412, 
            "name": "tunelp"
        }, 
        {
            "count": 608, 
            "name": "libbz2.so.1.0.4"
        }, 
        {
            "count": 118, 
            "name": "liblzma.so.5.0.0"
        }, 
        {
            "count": 238, 
            "name": "start-stop-daemon"
        }, 
        {
            "count": 6552, 
            "name": "dpkg"
        }, 
        {
            "count": 3144, 
            "name": "dpkg-deb"
        }, 
        {
            "count": 3362, 
            "name": "dpkg-divert"
        }, 
        {
            "count": 3560, 
            "name": "dpkg-query"
        }, 
        {
            "count": 2596, 
            "name": "dpkg-split"
        }, 
        {
            "count": 1202, 
            "name": "dpkg-statoverride"
        }, 
        {
            "count": 1348, 
            "name": "dpkg-trigger"
        }, 
        {
            "count": 1018, 
            "name": "update-alternatives"
        }, 
        {
            "count": 236, 
            "name": "libbz2.so.1.0"
        }, 
        {
            "count": 962, 
            "name": "login"
        }, 
        {
            "count": 738, 
            "name": "su"
        }, 
        {
            "count": 730, 
            "name": "libaudit.so.1.0.0"
        }, 
        {
            "count": 208, 
            "name": "faillog"
        }, 
        {
            "count": 138, 
            "name": "lastlog"
        }, 
        {
            "count": 702, 
            "name": "newgrp"
        }, 
        {
            "count": 18, 
            "name": "nologin"
        }, 
        {
            "count": 448, 
            "name": "libgcc_s.so.1"
        }, 
        {
            "count": 220, 
            "name": "apt"
        }, 
        {
            "count": 1762, 
            "name": "apt-cache"
        }, 
        {
            "count": 246, 
            "name": "apt-cdrom"
        }, 
        {
            "count": 266, 
            "name": "apt-config"
        }, 
        {
            "count": 688, 
            "name": "apt-get"
        }, 
        {
            "count": 610, 
            "name": "apt-mark"
        }, 
        {
            "count": 322, 
            "name": "apt-helper"
        }, 
        {
            "count": 506, 
            "name": "cdrom"
        }, 
        {
            "count": 160, 
            "name": "copy"
        }, 
        {
            "count": 222, 
            "name": "file"
        }, 
        {
            "count": 1040, 
            "name": "ftp"
        }, 
        {
            "count": 8118, 
            "name": "gpgv"
        }, 
        {
            "count": 1418, 
            "name": "http"
        }, 
        {
            "count": 1948, 
            "name": "mirror"
        }, 
        {
            "count": 870, 
            "name": "rred"
        }, 
        {
            "count": 476, 
            "name": "rsh"
        }, 
        {
            "count": 206, 
            "name": "store"
        }, 
        {
            "count": 118440, 
            "name": "libapt-pkg.so.5.0.0"
        }, 
        {
            "count": 10306, 
            "name": "libapt-private.so.0.0.0"
        }, 
        {
            "count": 5176, 
            "name": "libstdc++.so.6.0.21"
        }, 
        {
            "count": 808, 
            "name": "chage"
        }, 
        {
            "count": 826, 
            "name": "chfn"
        }, 
        {
            "count": 618, 
            "name": "chsh"
        }, 
        {
            "count": 370, 
            "name": "expiry"
        }, 
        {
            "count": 1422, 
            "name": "gpasswd"
        }, 
        {
            "count": 910, 
            "name": "passwd"
        }, 
        {
            "count": 576, 
            "name": "libsemanage.so.1"
        }, 
        {
            "count": 928, 
            "name": "chgpasswd"
        }, 
        {
            "count": 794, 
            "name": "chpasswd"
        }, 
        {
            "count": 730, 
            "name": "cppw"
        }, 
        {
            "count": 960, 
            "name": "groupadd"
        }, 
        {
            "count": 878, 
            "name": "groupdel"
        }, 
        {
            "count": 1240, 
            "name": "groupmod"
        }, 
        {
            "count": 868, 
            "name": "grpck"
        }, 
        {
            "count": 750, 
            "name": "grpconv"
        }, 
        {
            "count": 750, 
            "name": "grpunconv"
        }, 
        {
            "count": 1324, 
            "name": "newusers"
        }, 
        {
            "count": 772, 
            "name": "pwck"
        }, 
        {
            "count": 658, 
            "name": "pwconv"
        }, 
        {
            "count": 472, 
            "name": "pwunconv"
        }, 
        {
            "count": 2108, 
            "name": "useradd"
        }, 
        {
            "count": 1558, 
            "name": "userdel"
        }, 
        {
            "count": 2058, 
            "name": "usermod"
        }, 
        {
            "count": 886, 
            "name": "vipw"
        }, 
        {
            "count": 896, 
            "name": "findmnt"
        }, 
        {
            "count": 614, 
            "name": "mount"
        }, 
        {
            "count": 434, 
            "name": "umount"
        }, 
        {
            "count": 1698, 
            "name": "losetup"
        }, 
        {
            "count": 230, 
            "name": "swapoff"
        }, 
        {
            "count": 678, 
            "name": "swapon"
        }, 
        {
            "count": 3786, 
            "name": "libreadline.so.6.3"
        }, 
        {
            "count": 224, 
            "name": "libresolv-2.23.so"
        }, 
        {
            "count": 270, 
            "name": "libusb-0.1.so.4.4.4"
        }, 
        {
            "count": 18056, 
            "name": "gpg"
        }, 
        {
            "count": 770, 
            "name": "gpgsplit"
        }, 
        {
            "count": 1350, 
            "name": "gpgkeys_curl"
        }, 
        {
            "count": 754, 
            "name": "gpgkeys_finger"
        }, 
        {
            "count": 1494, 
            "name": "gpgkeys_hkp"
        }, 
        {
            "count": 504, 
            "name": "gpgkeys_ldap"
        }, 
        {
            "count": 3626, 
            "name": "libldap_r-2.4.so.2.10.5"
        }, 
        {
            "count": 24, 
            "name": "run-parts"
        }, 
        {
            "count": 2, 
            "name": "tempfile"
        }, 
        {
            "count": 2, 
            "name": "ischroot"
        }, 
        {
            "count": 2410, 
            "name": "eqn"
        }, 
        {
            "count": 1386, 
            "name": "groff"
        }, 
        {
            "count": 3522, 
            "name": "grops"
        }, 
        {
            "count": 1860, 
            "name": "grotty"
        }, 
        {
            "count": 2698, 
            "name": "pic"
        }, 
        {
            "count": 530, 
            "name": "preconv"
        }, 
        {
            "count": 398, 
            "name": "soelim"
        }, 
        {
            "count": 2712, 
            "name": "tbl"
        }, 
        {
            "count": 11670, 
            "name": "troff"
        }, 
        {
            "count": 1594, 
            "name": "dash"
        }, 
        {
            "count": 2772, 
            "name": "cpio"
        }, 
        {
            "count": 1368, 
            "name": "mt-gnu"
        }, 
        {
            "count": 276, 
            "name": "ping"
        }, 
        {
            "count": 316, 
            "name": "ping6"
        }, 
        {
            "count": 204, 
            "name": "libcap.so.2.24"
        }, 
        {
            "count": 528, 
            "name": "envsubst"
        }, 
        {
            "count": 532, 
            "name": "gettext"
        }, 
        {
            "count": 512, 
            "name": "ngettext"
        }, 
        {
            "count": 266, 
            "name": "whiptail"
        }, 
        {
            "count": 394, 
            "name": "libnewt.so.0.52.18"
        }, 
        {
            "count": 2486, 
            "name": "libpopt.so.0.0.0"
        }, 
        {
            "count": 1908, 
            "name": "less"
        }, 
        {
            "count": 32, 
            "name": "lessecho"
        }, 
        {
            "count": 170, 
            "name": "lesskey"
        }, 
        {
            "count": 149656, 
            "name": "libcrypto.so.1.0.0"
        }, 
        {
            "count": 2022, 
            "name": "libssl.so.1.0.0"
        }, 
        {
            "count": 7000, 
            "name": "wget"
        }, 
        {
            "count": 384, 
            "name": "libidn.so.11.6.15"
        }, 
        {
            "count": 750, 
            "name": "logrotate"
        }, 
        {
            "count": 2, 
            "name": "mawk"
        }, 
        {
            "count": 270, 
            "name": "crontab"
        }, 
        {
            "count": 446, 
            "name": "cron"
        }, 
        {
            "count": 1606, 
            "name": "netstat"
        }, 
        {
            "count": 1134, 
            "name": "ifconfig"
        }, 
        {
            "count": 244, 
            "name": "ipmaddr"
        }, 
        {
            "count": 310, 
            "name": "iptunnel"
        }, 
        {
            "count": 38, 
            "name": "mii-tool"
        }, 
        {
            "count": 94, 
            "name": "nameif"
        }, 
        {
            "count": 30, 
            "name": "plipconfig"
        }, 
        {
            "count": 256, 
            "name": "rarp"
        }, 
        {
            "count": 658, 
            "name": "route"
        }, 
        {
            "count": 272, 
            "name": "slattach"
        }, 
        {
            "count": 556, 
            "name": "arp"
        }, 
        {
            "count": 2, 
            "name": "bsd-from"
        }, 
        {
            "count": 2, 
            "name": "bsd-write"
        }, 
        {
            "count": 2, 
            "name": "calendar"
        }, 
        {
            "count": 2, 
            "name": "col"
        }, 
        {
            "count": 2, 
            "name": "colcrt"
        }, 
        {
            "count": 2, 
            "name": "colrm"
        }, 
        {
            "count": 2, 
            "name": "column"
        }, 
        {
            "count": 2, 
            "name": "hexdump"
        }, 
        {
            "count": 2, 
            "name": "look"
        }, 
        {
            "count": 2, 
            "name": "ncal"
        }, 
        {
            "count": 2, 
            "name": "printerbanner"
        }, 
        {
            "count": 2, 
            "name": "ul"
        }, 
        {
            "count": 1158, 
            "name": "ifup"
        }, 
        {
            "count": 630, 
            "name": "fuser"
        }, 
        {
            "count": 122, 
            "name": "killall"
        }, 
        {
            "count": 38, 
            "name": "peekfd"
        }, 
        {
            "count": 80, 
            "name": "prtstat"
        }, 
        {
            "count": 150, 
            "name": "pstree"
        }, 
        {
            "count": 106, 
            "name": "fstype"
        }, 
        {
            "count": 4, 
            "name": "halt"
        }, 
        {
            "count": 348, 
            "name": "ipconfig"
        }, 
        {
            "count": 942, 
            "name": "kinit.shared"
        }, 
        {
            "count": 44, 
            "name": "minips"
        }, 
        {
            "count": 110, 
            "name": "nfsmount"
        }, 
        {
            "count": 6, 
            "name": "nuke"
        }, 
        {
            "count": 4, 
            "name": "poweroff"
        }, 
        {
            "count": 4, 
            "name": "reboot"
        }, 
        {
            "count": 64, 
            "name": "resume"
        }, 
        {
            "count": 52, 
            "name": "run-init"
        }, 
        {
            "count": 1326, 
            "name": "sh.shared"
        }, 
        {
            "count": 194, 
            "name": "libip4tc.so.0.1.0"
        }, 
        {
            "count": 198, 
            "name": "libip6tc.so.0.1.0"
        }, 
        {
            "count": 324, 
            "name": "libxtables.so.11.0.0"
        }, 
        {
            "count": 958, 
            "name": "xtables-multi"
        }, 
        {
            "count": 32, 
            "name": "libnfnetlink.so.0.2.0"
        }, 
        {
            "count": 68, 
            "name": "nfnl_osf"
        }, 
        {
            "count": 526, 
            "name": "libkmod.so.2.3.0"
        }, 
        {
            "count": 590, 
            "name": "libpci.so.3.3.1"
        }, 
        {
            "count": 378, 
            "name": "lspci"
        }, 
        {
            "count": 94, 
            "name": "pcimodules"
        }, 
        {
            "count": 128, 
            "name": "setpci"
        }, 
        {
            "count": 280, 
            "name": "kill"
        }, 
        {
            "count": 1022, 
            "name": "ps"
        }, 
        {
            "count": 466, 
            "name": "libncurses.so.5.9"
        }, 
        {
            "count": 982, 
            "name": "libprocps.so.4.0.0"
        }, 
        {
            "count": 362, 
            "name": "sysctl"
        }, 
        {
            "count": 182, 
            "name": "free"
        }, 
        {
            "count": 296, 
            "name": "pgrep"
        }, 
        {
            "count": 444, 
            "name": "pmap"
        }, 
        {
            "count": 88, 
            "name": "pwdx"
        }, 
        {
            "count": 280, 
            "name": "skill"
        }, 
        {
            "count": 196, 
            "name": "slabtop"
        }, 
        {
            "count": 108, 
            "name": "tload"
        }, 
        {
            "count": 852, 
            "name": "top"
        }, 
        {
            "count": 68, 
            "name": "uptime"
        }, 
        {
            "count": 418, 
            "name": "vmstat"
        }, 
        {
            "count": 192, 
            "name": "watch"
        }, 
        {
            "count": 218, 
            "name": "w.procps"
        }, 
        {
            "count": 16, 
            "name": "libmagic.so.1.0.0"
        }, 
        {
            "count": 114, 
            "name": "biosdecode"
        }, 
        {
            "count": 514, 
            "name": "dmidecode"
        }, 
        {
            "count": 74, 
            "name": "ownership"
        }, 
        {
            "count": 82, 
            "name": "vpddecode"
        }, 
        {
            "count": 1126, 
            "name": "scp"
        }, 
        {
            "count": 2386, 
            "name": "sftp"
        }, 
        {
            "count": 11644, 
            "name": "ssh"
        }, 
        {
            "count": 5076, 
            "name": "ssh-add"
        }, 
        {
            "count": 5356, 
            "name": "ssh-agent"
        }, 
        {
            "count": 6396, 
            "name": "ssh-keygen"
        }, 
        {
            "count": 6424, 
            "name": "ssh-keyscan"
        }, 
        {
            "count": 6676, 
            "name": "ssh-keysign"
        }, 
        {
            "count": 5282, 
            "name": "ssh-pkcs11-helper"
        }, 
        {
            "count": 1628, 
            "name": "libedit.so.2.0.53"
        }, 
        {
            "count": 254, 
            "name": "libgssapi_krb5.so.2.2"
        }, 
        {
            "count": 1638, 
            "name": "lsof"
        }, 
        {
            "count": 3970, 
            "name": "nano"
        }, 
        {
            "count": 92, 
            "name": "xxd"
        }, 
        {
            "count": 234, 
            "name": "apt-extracttemplates"
        }, 
        {
            "count": 5716, 
            "name": "apt-ftparchive"
        }, 
        {
            "count": 384, 
            "name": "apt-sortpkgs"
        }, 
        {
            "count": 110, 
            "name": "dump"
        }, 
        {
            "count": 450, 
            "name": "libapt-inst.so.2.0.0"
        }, 
        {
            "count": 6282, 
            "name": "libdb-5.3.so"
        }, 
        {
            "count": 490, 
            "name": "xauth"
        }, 
        {
            "count": 12392, 
            "name": "libX11.so.6.3.0"
        }, 
        {
            "count": 94, 
            "name": "libXau.so.6.0.0"
        }, 
        {
            "count": 90, 
            "name": "libXext.so.6.4.0"
        }, 
        {
            "count": 6, 
            "name": "libXmuu.so.1.0.0"
        }, 
        {
            "count": 290, 
            "name": "bunzip2"
        }, 
        {
            "count": 290, 
            "name": "bzcat"
        }, 
        {
            "count": 290, 
            "name": "bzip2"
        }, 
        {
            "count": 94, 
            "name": "bzip2recover"
        }, 
        {
            "count": 8476, 
            "name": "openssl"
        }, 
        {
            "count": 728, 
            "name": "systemd-hwdb"
        }, 
        {
            "count": 5624, 
            "name": "udevadm"
        }, 
        {
            "count": 5470, 
            "name": "systemd-udevd"
        }, 
        {
            "count": 252, 
            "name": "ata_id"
        }, 
        {
            "count": 290, 
            "name": "cdrom_id"
        }, 
        {
            "count": 64, 
            "name": "collect"
        }, 
        {
            "count": 12, 
            "name": "mtd_probe"
        }, 
        {
            "count": 372, 
            "name": "scsi_id"
        }, 
        {
            "count": 34, 
            "name": "v4l_id"
        }, 
        {
            "count": 598, 
            "name": "telnet.netkit"
        }, 
        {
            "count": 3714, 
            "name": "info"
        }, 
        {
            "count": 238, 
            "name": "libdevmapper.so.1.02.1"
        }, 
        {
            "count": 548, 
            "name": "eject"
        }, 
        {
            "count": 24, 
            "name": "volname"
        }, 
        {
            "count": 38, 
            "name": "dmcrypt-get-device"
        }, 
        {
            "count": 10154, 
            "name": "vim.tiny"
        }, 
        {
            "count": 746, 
            "name": "libusb-1.0.so.0.1.0"
        }, 
        {
            "count": 788, 
            "name": "lsusb"
        }, 
        {
            "count": 170, 
            "name": "usbhid-dump"
        }, 
        {
            "count": 800, 
            "name": "host"
        }, 
        {
            "count": 88, 
            "name": "libbind9.so.140.0.10"
        }, 
        {
            "count": 11062, 
            "name": "libdns.so.162.1.3"
        }, 
        {
            "count": 304, 
            "name": "libisccfg.so.140.3.0"
        }, 
        {
            "count": 3398, 
            "name": "libisc.so.160.0.0"
        }, 
        {
            "count": 204, 
            "name": "liblwres.so.141.0.3"
        }, 
        {
            "count": 138, 
            "name": "time"
        }, 
        {
            "count": 419282, 
            "name": "libglib-2.0.so.0.4800.2"
        }, 
        {
            "count": 48, 
            "name": "gio-querymodules"
        }, 
        {
            "count": 344, 
            "name": "glib-compile-resources"
        }, 
        {
            "count": 600, 
            "name": "glib-compile-schemas"
        }, 
        {
            "count": 13272, 
            "name": "libgio-2.0.so.0.4800.2"
        }, 
        {
            "count": 592, 
            "name": "libgmodule-2.0.so.0.4800.2"
        }, 
        {
            "count": 82574, 
            "name": "libgobject-2.0.so.0.4800.2"
        }, 
        {
            "count": 58, 
            "name": "libapparmor.so.1.4.0"
        }, 
        {
            "count": 41036, 
            "name": "libdbus-1.so.3.14.6"
        }, 
        {
            "count": 232, 
            "name": "libexpat.so.1.6.0"
        }, 
        {
            "count": 38, 
            "name": "dbus-cleanup-sockets"
        }, 
        {
            "count": 5222, 
            "name": "dbus-daemon"
        }, 
        {
            "count": 282, 
            "name": "dbus-monitor"
        }, 
        {
            "count": 22, 
            "name": "dbus-run-session"
        }, 
        {
            "count": 228, 
            "name": "dbus-send"
        }, 
        {
            "count": 62, 
            "name": "dbus-update-activation-environment"
        }, 
        {
            "count": 36, 
            "name": "dbus-uuidgen"
        }, 
        {
            "count": 790, 
            "name": "dbus-daemon-launch-helper"
        }, 
        {
            "count": 156, 
            "name": "libcap-ng.so.0.0.0"
        }, 
        {
            "count": 712, 
            "name": "netkit-ftp"
        }, 
        {
            "count": 654, 
            "name": "bc"
        }, 
        {
            "count": 752, 
            "name": "catman"
        }, 
        {
            "count": 688, 
            "name": "lexgrog"
        }, 
        {
            "count": 2238, 
            "name": "man"
        }, 
        {
            "count": 1774, 
            "name": "mandb"
        }, 
        {
            "count": 678, 
            "name": "manpath"
        }, 
        {
            "count": 974, 
            "name": "whatis"
        }, 
        {
            "count": 166, 
            "name": "globbing"
        }, 
        {
            "count": 6288, 
            "name": "libman-2.7.5.so"
        }, 
        {
            "count": 936, 
            "name": "libmandb-2.7.5.so"
        }, 
        {
            "count": 130, 
            "name": "manconv"
        }, 
        {
            "count": 868, 
            "name": "zsoelim"
        }, 
        {
            "count": 534, 
            "name": "libgdbm.so.3.0.0"
        }, 
        {
            "count": 1640, 
            "name": "libpipeline.so.1.4.1"
        }, 
        {
            "count": 54, 
            "name": "accessdb"
        }, 
        {
            "count": 1000, 
            "name": "dig"
        }, 
        {
            "count": 1000, 
            "name": "nslookup"
        }, 
        {
            "count": 624, 
            "name": "nsupdate"
        }, 
        {
            "count": 62, 
            "name": "libkrb5.so.3.3"
        }, 
        {
            "count": 110, 
            "name": "fc-cache"
        }, 
        {
            "count": 92, 
            "name": "fc-cat"
        }, 
        {
            "count": 52, 
            "name": "fc-list"
        }, 
        {
            "count": 50, 
            "name": "fc-match"
        }, 
        {
            "count": 62, 
            "name": "fc-pattern"
        }, 
        {
            "count": 44, 
            "name": "fc-query"
        }, 
        {
            "count": 40, 
            "name": "fc-scan"
        }, 
        {
            "count": 42, 
            "name": "fc-validate"
        }, 
        {
            "count": 2298, 
            "name": "libfontconfig.so.1.9.0"
        }, 
        {
            "count": 1212, 
            "name": "libfreetype.so.6.12.1"
        }, 
        {
            "count": 86, 
            "name": "funzip"
        }, 
        {
            "count": 822, 
            "name": "unzip"
        }, 
        {
            "count": 522, 
            "name": "unzipsfx"
        }, 
        {
            "count": 822, 
            "name": "zipinfo"
        }, 
        {
            "count": 112, 
            "name": "libgdk_pixbuf-2.0.so.0.3200.2"
        }, 
        {
            "count": 18, 
            "name": "gtk-query-immodules-2.0"
        }, 
        {
            "count": 444, 
            "name": "gtk-update-icon-cache"
        }, 
        {
            "count": 12, 
            "name": "libgtk-x11-2.0.so.0.2400.30"
        }, 
        {
            "count": 18, 
            "name": "libpango-1.0.so.0.3800.1"
        }, 
        {
            "count": 336, 
            "name": "at"
        }, 
        {
            "count": 150, 
            "name": "atd"
        }, 
        {
            "count": 1752, 
            "name": "sudo"
        }, 
        {
            "count": 488, 
            "name": "sudoreplay"
        }, 
        {
            "count": 6684, 
            "name": "libsudo_util.so.0.0.0"
        }, 
        {
            "count": 88, 
            "name": "sesh"
        }, 
        {
            "count": 1776, 
            "name": "visudo"
        }, 
        {
            "count": 866, 
            "name": "update-mime-database.real"
        }, 
        {
            "count": 13888, 
            "name": "libxml2.so.2.9.3"
        }, 
        {
            "count": 56, 
            "name": "acpi_listen"
        }, 
        {
            "count": 368, 
            "name": "acpid"
        }, 
        {
            "count": 548, 
            "name": "dc"
        }, 
        {
            "count": 5458, 
            "name": "rsync"
        }, 
        {
            "count": 700, 
            "name": "fatlabel"
        }, 
        {
            "count": 684, 
            "name": "fsck.fat"
        }, 
        {
            "count": 120, 
            "name": "mkfs.fat"
        }, 
        {
            "count": 410, 
            "name": "x86_64-linux-gnu-addr2line"
        }, 
        {
            "count": 1020, 
            "name": "x86_64-linux-gnu-ar"
        }, 
        {
            "count": 6948, 
            "name": "x86_64-linux-gnu-as"
        }, 
        {
            "count": 338, 
            "name": "x86_64-linux-gnu-c++filt"
        }, 
        {
            "count": 65602, 
            "name": "x86_64-linux-gnu-dwp"
        }, 
        {
            "count": 522, 
            "name": "x86_64-linux-gnu-elfedit"
        }, 
        {
            "count": 1724, 
            "name": "x86_64-linux-gnu-gprof"
        }, 
        {
            "count": 8842, 
            "name": "x86_64-linux-gnu-ld.bfd"
        }, 
        {
            "count": 68242, 
            "name": "x86_64-linux-gnu-ld.gold"
        }, 
        {
            "count": 576, 
            "name": "x86_64-linux-gnu-nm"
        }, 
        {
            "count": 4922, 
            "name": "x86_64-linux-gnu-objcopy"
        }, 
        {
            "count": 6916, 
            "name": "x86_64-linux-gnu-objdump"
        }, 
        {
            "count": 1020, 
            "name": "x86_64-linux-gnu-ranlib"
        }, 
        {
            "count": 5392, 
            "name": "x86_64-linux-gnu-readelf"
        }, 
        {
            "count": 418, 
            "name": "x86_64-linux-gnu-size"
        }, 
        {
            "count": 388, 
            "name": "x86_64-linux-gnu-strings"
        }, 
        {
            "count": 4922, 
            "name": "x86_64-linux-gnu-strip"
        }, 
        {
            "count": 3768, 
            "name": "libbfd-2.26.1-system.so"
        }, 
        {
            "count": 40, 
            "name": "bdftopcf"
        }, 
        {
            "count": 20, 
            "name": "bdftruncate"
        }, 
        {
            "count": 736, 
            "name": "fonttosfnt"
        }, 
        {
            "count": 400, 
            "name": "mkfontscale"
        }, 
        {
            "count": 260, 
            "name": "ucs2any"
        }, 
        {
            "count": 128, 
            "name": "libfontenc.so.1.0.0"
        }, 
        {
            "count": 234, 
            "name": "libXfont.so.1.4.1"
        }, 
        {
            "count": 2678, 
            "name": "libparted.so.2.0.1"
        }, 
        {
            "count": 982, 
            "name": "parted"
        }, 
        {
            "count": 32, 
            "name": "partprobe"
        }, 
        {
            "count": 1772, 
            "name": "make"
        }, 
        {
            "count": 172, 
            "name": "libpcap.so.1.7.4"
        }, 
        {
            "count": 276, 
            "name": "chat"
        }, 
        {
            "count": 5796, 
            "name": "pppd"
        }, 
        {
            "count": 80, 
            "name": "pppdump"
        }, 
        {
            "count": 142, 
            "name": "pppoe-discovery"
        }, 
        {
            "count": 50, 
            "name": "pppstats"
        }, 
        {
            "count": 1072, 
            "name": "libnl-3.so.200.22.0"
        }, 
        {
            "count": 14, 
            "name": "libnl-genl-3.so.200.22.0"
        }, 
        {
            "count": 114, 
            "name": "libpcsclite.so.1.0.0"
        }, 
        {
            "count": 1160, 
            "name": "wpa_cli"
        }, 
        {
            "count": 39738, 
            "name": "wpa_supplicant"
        }, 
        {
            "count": 996, 
            "name": "wpa_passphrase"
        }, 
        {
            "count": 94, 
            "name": "xinit"
        }, 
        {
            "count": 460, 
            "name": "hdparm"
        }, 
        {
            "count": 290, 
            "name": "anacron"
        }, 
        {
            "count": 214, 
            "name": "aconnect"
        }, 
        {
            "count": 388, 
            "name": "alsabat"
        }, 
        {
            "count": 716, 
            "name": "alsaloop"
        }, 
        {
            "count": 510, 
            "name": "alsamixer"
        }, 
        {
            "count": 26, 
            "name": "alsatplg"
        }, 
        {
            "count": 36, 
            "name": "alsaucm"
        }, 
        {
            "count": 70, 
            "name": "amidi"
        }, 
        {
            "count": 696, 
            "name": "amixer"
        }, 
        {
            "count": 580, 
            "name": "aplay"
        }, 
        {
            "count": 98, 
            "name": "aplaymidi"
        }, 
        {
            "count": 212, 
            "name": "arecordmidi"
        }, 
        {
            "count": 56, 
            "name": "aseqdump"
        }, 
        {
            "count": 76, 
            "name": "aseqnet"
        }, 
        {
            "count": 58, 
            "name": "iecset"
        }, 
        {
            "count": 236, 
            "name": "speaker-test"
        }, 
        {
            "count": 5580, 
            "name": "libasound.so.2.0.0"
        }, 
        {
            "count": 222, 
            "name": "libfftw3.so.3.4.4"
        }, 
        {
            "count": 170, 
            "name": "libformw.so.5.9"
        }, 
        {
            "count": 156, 
            "name": "libmenuw.so.5.9"
        }, 
        {
            "count": 2434, 
            "name": "liboss4-salsa.so.2.0.0"
        }, 
        {
            "count": 32, 
            "name": "libpanelw.so.5.9"
        }, 
        {
            "count": 24, 
            "name": "libsamplerate.so.0.1.8"
        }, 
        {
            "count": 1488, 
            "name": "alsactl"
        }, 
        {
            "count": 2526, 
            "name": "aspell"
        }, 
        {
            "count": 14, 
            "name": "prezip-bin"
        }, 
        {
            "count": 14, 
            "name": "word-list-compress"
        }, 
        {
            "count": 23534, 
            "name": "libaspell.so.15.2.0"
        }, 
        {
            "count": 14, 
            "name": "gst-plugin-scanner"
        }, 
        {
            "count": 76, 
            "name": "libgstreamer-0.10.so.0.30.0"
        }, 
        {
            "count": 410, 
            "name": "libavahi-common.so.3.5.3"
        }, 
        {
            "count": 2940, 
            "name": "libavahi-core.so.7.0.2"
        }, 
        {
            "count": 628, 
            "name": "libdaemon.so.0.5.0"
        }, 
        {
            "count": 2138, 
            "name": "avahi-daemon"
        }, 
        {
            "count": 140, 
            "name": "arping"
        }, 
        {
            "count": 38, 
            "name": "tracepath"
        }, 
        {
            "count": 50, 
            "name": "tracepath6"
        }, 
        {
            "count": 76, 
            "name": "traceroute6.iputils"
        }, 
        {
            "count": 2014, 
            "name": "zip"
        }, 
        {
            "count": 1132, 
            "name": "zipcloak"
        }, 
        {
            "count": 1134, 
            "name": "zipnote"
        }, 
        {
            "count": 1166, 
            "name": "zipsplit"
        }, 
        {
            "count": 15548, 
            "name": "tcpdump"
        }, 
        {
            "count": 138, 
            "name": "pdfdetach"
        }, 
        {
            "count": 78, 
            "name": "pdffonts"
        }, 
        {
            "count": 464, 
            "name": "pdfimages"
        }, 
        {
            "count": 398, 
            "name": "pdfinfo"
        }, 
        {
            "count": 68, 
            "name": "pdfseparate"
        }, 
        {
            "count": 1446, 
            "name": "pdftocairo"
        }, 
        {
            "count": 1340, 
            "name": "pdftohtml"
        }, 
        {
            "count": 76, 
            "name": "pdftoppm"
        }, 
        {
            "count": 108, 
            "name": "pdftops"
        }, 
        {
            "count": 318, 
            "name": "pdftotext"
        }, 
        {
            "count": 312, 
            "name": "pdfunite"
        }, 
        {
            "count": 650, 
            "name": "libcairo.so.2.11400.6"
        }, 
        {
            "count": 122, 
            "name": "liblcms2.so.2.0.6"
        }, 
        {
            "count": 168548, 
            "name": "libpoppler.so.58.0.0"
        }, 
        {
            "count": 836, 
            "name": "libwrap.so.0.7.6"
        }, 
        {
            "count": 26, 
            "name": "safe_finger"
        }, 
        {
            "count": 30, 
            "name": "tcpd"
        }, 
        {
            "count": 320, 
            "name": "tcpdchk"
        }, 
        {
            "count": 218, 
            "name": "tcpdmatch"
        }, 
        {
            "count": 72, 
            "name": "try-from"
        }, 
        {
            "count": 2962, 
            "name": "strace"
        }, 
        {
            "count": 566, 
            "name": "ed"
        }, 
        {
            "count": 732, 
            "name": "ntpdate"
        }, 
        {
            "count": 604, 
            "name": "libiw.so.30"
        }, 
        {
            "count": 296, 
            "name": "iwconfig"
        }, 
        {
            "count": 36, 
            "name": "iwevent"
        }, 
        {
            "count": 66, 
            "name": "iwgetid"
        }, 
        {
            "count": 158, 
            "name": "iwlist"
        }, 
        {
            "count": 60, 
            "name": "iwpriv"
        }, 
        {
            "count": 58, 
            "name": "iwspy"
        }, 
        {
            "count": 154, 
            "name": "gconf-merge-tree"
        }, 
        {
            "count": 1686, 
            "name": "gconftool-2"
        }, 
        {
            "count": 192, 
            "name": "gsettings-data-convert"
        }, 
        {
            "count": 3224, 
            "name": "libgconf-2.so.4.1.5"
        }, 
        {
            "count": 4792, 
            "name": "devdump"
        }, 
        {
            "count": 9094, 
            "name": "genisoimage"
        }, 
        {
            "count": 4872, 
            "name": "isodump"
        }, 
        {
            "count": 3324, 
            "name": "isoinfo"
        }, 
        {
            "count": 4904, 
            "name": "isovfy"
        }, 
        {
            "count": 204, 
            "name": "mkzftree"
        }, 
        {
            "count": 16250, 
            "name": "lshw"
        }, 
        {
            "count": 214, 
            "name": "libgcrypt.so.20.0.5"
        }, 
        {
            "count": 86, 
            "name": "cvt"
        }, 
        {
            "count": 36, 
            "name": "gtf"
        }, 
        {
            "count": 362, 
            "name": "libdrm.so.2.4.0"
        }, 
        {
            "count": 42, 
            "name": "libpciaccess.so.0.11.1"
        }, 
        {
            "count": 474, 
            "name": "libpixman-1.so.0.33.6"
        }, 
        {
            "count": 124, 
            "name": "libXdmcp.so.6.0.0"
        }, 
        {
            "count": 6, 
            "name": "libxshmfence.so.1.0.0"
        }, 
        {
            "count": 39872, 
            "name": "Xorg"
        }, 
        {
            "count": 32, 
            "name": "synclient"
        }, 
        {
            "count": 90, 
            "name": "syndaemon"
        }, 
        {
            "count": 656, 
            "name": "libXi.so.6.1.0"
        }, 
        {
            "count": 76, 
            "name": "libXtst.so.6.1.0"
        }, 
        {
            "count": 78, 
            "name": "isdv4-serial-debugger"
        }, 
        {
            "count": 88, 
            "name": "isdv4-serial-inputattach"
        }, 
        {
            "count": 452, 
            "name": "xsetwacom"
        }, 
        {
            "count": 4, 
            "name": "libXinerama.so.1.0.0"
        }, 
        {
            "count": 94, 
            "name": "libXrandr.so.2.2.0"
        }, 
        {
            "count": 9440, 
            "name": "ltrace"
        }, 
        {
            "count": 118, 
            "name": "libelf-0.165.so"
        }, 
        {
            "count": 614, 
            "name": "mtr"
        }, 
        {
            "count": 6290, 
            "name": "busybox"
        }, 
        {
            "count": 26, 
            "name": "libx86.so.1"
        }, 
        {
            "count": 148, 
            "name": "vbetool"
        }, 
        {
            "count": 98, 
            "name": "vmwarectrl"
        }, 
        {
            "count": 44, 
            "name": "mscompress"
        }, 
        {
            "count": 26, 
            "name": "msexpand"
        }, 
        {
            "count": 3170, 
            "name": "telinit"
        }, 
        {
            "count": 136, 
            "name": "libcgmanager.so.0.0.0"
        }, 
        {
            "count": 222, 
            "name": "libjson-c.so.2.0.0"
        }, 
        {
            "count": 2058, 
            "name": "libnih-dbus.so.1.0.0"
        }, 
        {
            "count": 32902, 
            "name": "libnih.so.1.0.0"
        }, 
        {
            "count": 5378, 
            "name": "initctl"
        }, 
        {
            "count": 7284, 
            "name": "upstart"
        }, 
        {
            "count": 3896, 
            "name": "upstart-dbus-bridge"
        }, 
        {
            "count": 3798, 
            "name": "upstart-event-bridge"
        }, 
        {
            "count": 4144, 
            "name": "upstart-file-bridge"
        }, 
        {
            "count": 2438, 
            "name": "upstart-local-bridge"
        }, 
        {
            "count": 3866, 
            "name": "upstart-socket-bridge"
        }, 
        {
            "count": 2262, 
            "name": "upstart-udev-bridge"
        }, 
        {
            "count": 382, 
            "name": "foomatic-combo-xml"
        }, 
        {
            "count": 1118, 
            "name": "foomatic-perl-data"
        }, 
        {
            "count": 114, 
            "name": "gnome-keyring-3"
        }, 
        {
            "count": 31908, 
            "name": "gnome-keyring-daemon"
        }, 
        {
            "count": 1654, 
            "name": "libgck-1.so.0.0.0"
        }, 
        {
            "count": 636, 
            "name": "libgcr-base-3.so.1.0.0"
        }, 
        {
            "count": 240, 
            "name": "resize"
        }, 
        {
            "count": 5860, 
            "name": "xterm"
        }, 
        {
            "count": 18, 
            "name": "libICE.so.6.3.0"
        }, 
        {
            "count": 4, 
            "name": "libXaw7.so.7.0.0"
        }, 
        {
            "count": 436, 
            "name": "libXft.so.2.3.2"
        }, 
        {
            "count": 170, 
            "name": "libXmu.so.6.2.0"
        }, 
        {
            "count": 656, 
            "name": "libXpm.so.4.11.0"
        }, 
        {
            "count": 602, 
            "name": "libXt.so.6.0.0"
        }, 
        {
            "count": 173218, 
            "name": "gdb"
        }, 
        {
            "count": 84, 
            "name": "libbabeltrace-ctf.so.1.0.0"
        }, 
        {
            "count": 96, 
            "name": "libbabeltrace.so.1.0.0"
        }, 
        {
            "count": 111532, 
            "name": "libpython3.5m.so.1.0"
        }, 
        {
            "count": 19908, 
            "name": "nmcli"
        }, 
        {
            "count": 50, 
            "name": "nm-online"
        }, 
        {
            "count": 2302, 
            "name": "nmtui"
        }, 
        {
            "count": 58, 
            "name": "nm-dhcp-helper"
        }, 
        {
            "count": 296, 
            "name": "nm-dispatcher"
        }, 
        {
            "count": 79410, 
            "name": "nm-iface-helper"
        }, 
        {
            "count": 506, 
            "name": "libgnutls.so.30.6.2"
        }, 
        {
            "count": 536, 
            "name": "libgudev-1.0.so.0.2.0"
        }, 
        {
            "count": 196, 
            "name": "libndp.so.0.0.2"
        }, 
        {
            "count": 21018, 
            "name": "libnm.so.0.1.0"
        }, 
        {
            "count": 140, 
            "name": "libpolkit-agent-1.so.0.0.0"
        }, 
        {
            "count": 104, 
            "name": "libpolkit-gobject-1.so.0.0.0"
        }, 
        {
            "count": 468, 
            "name": "libsoup-2.4.so.1.7.0"
        }, 
        {
            "count": 285894, 
            "name": "NetworkManager"
        }, 
        {
            "count": 3704, 
            "name": "readom"
        }, 
        {
            "count": 10880, 
            "name": "wodim"
        }, 
        {
            "count": 1534, 
            "name": "netscsid"
        }, 
        {
            "count": 96, 
            "name": "pcmcia-check-broken-cis"
        }, 
        {
            "count": 154, 
            "name": "pcmcia-socket-startup"
        }, 
        {
            "count": 170, 
            "name": "pccardctl"
        }, 
        {
            "count": 80, 
            "name": "libbsd.so.0.8.2"
        }, 
        {
            "count": 674, 
            "name": "cifsdd"
        }, 
        {
            "count": 14286, 
            "name": "rpcclient"
        }, 
        {
            "count": 392, 
            "name": "smbcacls"
        }, 
        {
            "count": 356, 
            "name": "smbclient"
        }, 
        {
            "count": 76, 
            "name": "smbcquotas"
        }, 
        {
            "count": 36, 
            "name": "smbget"
        }, 
        {
            "count": 88, 
            "name": "smbspool"
        }, 
        {
            "count": 246, 
            "name": "smbspool_krb5_wrapper"
        }, 
        {
            "count": 68, 
            "name": "smbtree"
        }, 
        {
            "count": 128, 
            "name": "libsamba-debug.so.0"
        }, 
        {
            "count": 1050, 
            "name": "libarchive.so.13.1.2"
        }, 
        {
            "count": 546, 
            "name": "libdcerpc-binding.so.0.0.1"
        }, 
        {
            "count": 8, 
            "name": "libgensec.so.0.0.1"
        }, 
        {
            "count": 348, 
            "name": "libndr-nbt.so.0.0.1"
        }, 
        {
            "count": 318, 
            "name": "libndr.so.0.0.5"
        }, 
        {
            "count": 406, 
            "name": "libndr-standard.so.0.0.1"
        }, 
        {
            "count": 2, 
            "name": "libroken.so.18.1.0"
        }, 
        {
            "count": 440, 
            "name": "libsamba-credentials.so.0.0.1"
        }, 
        {
            "count": 704, 
            "name": "libsamba-hostconfig.so.0.0.1"
        }, 
        {
            "count": 44, 
            "name": "libsamba-passdb.so.0.24.1"
        }, 
        {
            "count": 2610, 
            "name": "libsamba-util.so.0.0.1"
        }, 
        {
            "count": 2802, 
            "name": "libsmbclient-raw.so.0.0.1"
        }, 
        {
            "count": 362, 
            "name": "libsmbclient.so.0.2.3"
        }, 
        {
            "count": 338, 
            "name": "libsmbconf.so.0"
        }, 
        {
            "count": 892, 
            "name": "libtalloc.so.2.1.5"
        }, 
        {
            "count": 112, 
            "name": "libtevent.so.0.9.28"
        }, 
        {
            "count": 8, 
            "name": "libtevent-util.so.0.0.1"
        }, 
        {
            "count": 216, 
            "name": "libcliauth.so.0"
        }, 
        {
            "count": 200, 
            "name": "libcli-cldap.so.0"
        }, 
        {
            "count": 52, 
            "name": "libcli-ldap.so.0"
        }, 
        {
            "count": 24, 
            "name": "libcli-smb-common.so.0"
        }, 
        {
            "count": 248, 
            "name": "libcli-spoolss.so.0"
        }, 
        {
            "count": 4, 
            "name": "libcmdline-credentials.so.0"
        }, 
        {
            "count": 672, 
            "name": "libdcerpc-samba.so.0"
        }, 
        {
            "count": 8, 
            "name": "libevents.so.0"
        }, 
        {
            "count": 52, 
            "name": "libgenrand.so.0"
        }, 
        {
            "count": 274, 
            "name": "libgse.so.0"
        }, 
        {
            "count": 166, 
            "name": "liblibcli-lsa3.so.0"
        }, 
        {
            "count": 120, 
            "name": "liblibcli-netlogon3.so.0"
        }, 
        {
            "count": 8774, 
            "name": "liblibsmb.so.0"
        }, 
        {
            "count": 766, 
            "name": "libmsrpc3.so.0"
        }, 
        {
            "count": 90, 
            "name": "libpopt-samba3.so.0"
        }, 
        {
            "count": 44, 
            "name": "libsamba3-util.so.0"
        }, 
        {
            "count": 408, 
            "name": "libsamba-security.so.0"
        }, 
        {
            "count": 120, 
            "name": "libsamba-sockets.so.0"
        }, 
        {
            "count": 166, 
            "name": "libsmbregistry.so.0"
        }, 
        {
            "count": 82, 
            "name": "libtrusts-util.so.0"
        }, 
        {
            "count": 326, 
            "name": "libutil-cmdline.so.0"
        }, 
        {
            "count": 24, 
            "name": "libutil-reg.so.0"
        }, 
        {
            "count": 112, 
            "name": "inputattach"
        }, 
        {
            "count": 90, 
            "name": "btcflash"
        }, 
        {
            "count": 44, 
            "name": "dvd-ram-control"
        }, 
        {
            "count": 338, 
            "name": "dvd+rw-booktype"
        }, 
        {
            "count": 118, 
            "name": "dvd+rw-mediainfo"
        }, 
        {
            "count": 38, 
            "name": "rpl8"
        }, 
        {
            "count": 68, 
            "name": "hp"
        }, 
        {
            "count": 98, 
            "name": "libhpmud.so.0.0.6"
        }, 
        {
            "count": 56, 
            "name": "paperconf"
        }, 
        {
            "count": 102, 
            "name": "libpaper.so.1.1.2"
        }, 
        {
            "count": 354, 
            "name": "avahi-autoipd"
        }, 
        {
            "count": 1438, 
            "name": "lowntfs-3g"
        }, 
        {
            "count": 2546, 
            "name": "ntfs-3g"
        }, 
        {
            "count": 22, 
            "name": "ntfs-3g.probe"
        }, 
        {
            "count": 642, 
            "name": "ntfs-3g.secaudit"
        }, 
        {
            "count": 106, 
            "name": "ntfs-3g.usermap"
        }, 
        {
            "count": 164, 
            "name": "ntfscat"
        }, 
        {
            "count": 212, 
            "name": "ntfscluster"
        }, 
        {
            "count": 328, 
            "name": "ntfscmp"
        }, 
        {
            "count": 240, 
            "name": "ntfsfallocate"
        }, 
        {
            "count": 342, 
            "name": "ntfsfix"
        }, 
        {
            "count": 376, 
            "name": "ntfsinfo"
        }, 
        {
            "count": 208, 
            "name": "ntfsls"
        }, 
        {
            "count": 188, 
            "name": "ntfsmove"
        }, 
        {
            "count": 200, 
            "name": "ntfstruncate"
        }, 
        {
            "count": 352, 
            "name": "ntfswipe"
        }, 
        {
            "count": 93012, 
            "name": "libntfs-3g.so.861.0.0"
        }, 
        {
            "count": 636, 
            "name": "mkntfs"
        }, 
        {
            "count": 510, 
            "name": "ntfsclone"
        }, 
        {
            "count": 260, 
            "name": "ntfscp"
        }, 
        {
            "count": 190, 
            "name": "ntfslabel"
        }, 
        {
            "count": 586, 
            "name": "ntfsresize"
        }, 
        {
            "count": 318, 
            "name": "ntfsundelete"
        }, 
        {
            "count": 190, 
            "name": "ntfsdecrypt"
        }, 
        {
            "count": 1028, 
            "name": "desktop-file-install"
        }, 
        {
            "count": 810, 
            "name": "desktop-file-validate"
        }, 
        {
            "count": 124, 
            "name": "update-desktop-database"
        }, 
        {
            "count": 212, 
            "name": "libgs.so.9.18"
        }
    ]
}