{
    "id": 34394, 
    "sources": [
        {
            "count": 6, 
            "name": "libfdisk.so.1.1.0"
        }, 
        {
            "count": 2, 
            "name": "gpg"
        }, 
        {
            "count": 2, 
            "name": "troff"
        }, 
        {
            "count": 26, 
            "name": "libc-2.23.so"
        }, 
        {
            "count": 2, 
            "name": "ssh-agent"
        }, 
        {
            "count": 10, 
            "name": "vim.tiny"
        }, 
        {
            "count": 18, 
            "name": "libpipeline.so.1.4.1"
        }, 
        {
            "count": 4, 
            "name": "x86_64-linux-gnu-dwp"
        }, 
        {
            "count": 4, 
            "name": "x86_64-linux-gnu-ld.gold"
        }, 
        {
            "count": 4, 
            "name": "libreadline.so.6.3"
        }, 
        {
            "count": 8, 
            "name": "Xorg"
        }, 
        {
            "count": 2, 
            "name": "busybox"
        }, 
        {
            "count": 4, 
            "name": "xterm"
        }
    ]
}